{
  "INDIVIDUAL": "Birey",
  "MERCHANT": "Mağaza",
  "REFUNDPOINT": "İade Noktası",
  "CUSTOM": "Gümrük",
  "TAXFREE": "Taxfree",
  "TAXOFFICE": "Vergi Dairesi",
  "TOURGUIDE": "Tur Rehberi",
  "TRAVELLER": "Turist",

  "Missing.ProductGroup.Title": "Product Group is missing",
  "Missing.ProductGroup.Message": "Please create a product group to continue.",

  "MerchantTypeCode.HEADQUARTER": "Genel Merkez",
  "MerchantTypeCode.STORE": "Mağaza",
  "MerchantTypeCode.FRANCHISE": "Franchise",

  "Merchant.personalCompany": "Şahıs şirketi",

  "CRM.typeCode": "Tip",
  "CRM.vatNumber": "Vergi Numarası",
  "CRM.externalStoreIdentifier": "Mağaza Tanımlayıcısı",
  "CRM.openHeadquarter": "Genel merkezi açmak igçin tıklayın",
  "CRM.Details": "Detaylar",
  "CRM.SubOrganization": "Mağazalar",
  "CRM.Merchant.SubOrganization": "Mağazalar",
  "CRM.RefundPoint.SubOrganization": "İade noktaları",
  "CRM.TaxFree.SubOrganization": "Taxfree noktaları",
  "CRM.ProductGroups": "Ürün Grupları",
  "CRM.Affiliations": "Bağlılıklar",
  "CRM.Contracts": "Kontratlar",
  "CRM.roleName": "Rol",

  "Form.Merchant.name": "Ünvan",
  "Form.Merchant.chainCodeId": "Marka",
  "Form.Merchant.vatNumber": "Vergi Numarası",
  "Form.Merchant.taxOfficeId": "Vergi Dairesi",
  "Form.Merchant.externalStoreIdentifier": "Mağaza Kodu",
  "Form.Merchant.parentId": "Ana Mağaza",

  "Form.Merchant.typeCode": "Tip",
  "Form.Merchant.typeCode.ui:placeholder": "Tip seçin",
  "Form.Merchant.typeCode.HEADQUARTER": "Genel Merkez",
  "Form.Merchant.typeCode.STORE": "Mağaza",
  "Form.Merchant.typeCode.FRANCHISE": "Franchise",
  "Form.Merchant.isPersonalCompany": "Şahıs Şirketi",

  "Form.Merchant.productGroup": "Ürün Grubu",
  "Form.Merchant.productGroup.active": "Aktif",
  "Form.Merchant.productGroup.inactive": "Pasif",
  "Form.Merchant.productGroup.isDefault": "Varsayılan ürün grubu",
  "Form.Merchant.productGroupId": "Ürün Grubu",
  "Form.Merchant.productGroups": "Ürün Grupları",
  "Form.Merchant.productGroup.update": "Ürün Grubunu Güncelle",
  "Form.Merchant.productGroup.default": "Varsayılan Ürün Grubunu Ayarla",
  "Form.Merchant.productGroup.default.description": "Bu ürün grubunu varsayılan ürün grubun olarak ayarla",
  "Form.Merchant.productGroup.create": "Ürün Grubu Ekle",
  "Form.Merchant.productGroup.delete": "Ürün Grubunu Sil",
  "Form.Merchant.productGroup.delete.confirm": "Bu ürün grubunu silmek istediğinize emin misiniz?",

  "Form.Merchant.Create": "Mağazayı Oluştur",
  "Form.Merchant.Update": "Mağazayı Güncelle",

  "Form.RefundPoint.name": "Ünvan",
  "Form.RefundPoint.vatNumber": "Vergi Numarası",
  "Form.RefundPoint.taxOfficeId": "Vergi Dairesi",
  "Form.RefundPoint.externalStoreIdentifier": "İade Noktası Kodu",
  "Form.RefundPoint.parentId": "Ana Nokta",

  "Form.RefundPoint.typeCode": "Tip",
  "Form.RefundPoint.typeCode.ui:placeholder": "Tip seçin",
  "Form.RefundPoint.typeCode.HEADQUARTER": "Genel merkez",
  "Form.RefundPoint.typeCode.REFUNDPOINT": "İade noktası",

  "Form.RefundPoint.Create": "İade Noktası Oluştur",
  "Form.RefundPoint.Update": "İade Noktası Güncelle",

  "Form.TaxFree.name": "Ünvan",
  "Form.TaxFree.vatNumber": "Vergi Numarası",
  "Form.TaxFree.taxOfficeId": "Vergi Dairesi",
  "Form.TaxFree.externalStoreIdentifier": "Taxfree Kodu",
  "Form.TaxFree.parentId": "Ana Nokta",

  "Form.TaxFree.typeCode": "Tip",
  "Form.TaxFree.typeCode.ui:placeholder": "Tip seçin",
  "Form.TaxFree.typeCode.HEADQUARTER": "Genel Merkez",
  "Form.TaxFree.typeCode.TAXFREE": "Tax Free",

  "Form.TaxFree.Create": "Tax Free Oluştur",
  "Form.TaxFree.Update": "Tax Free Güncelle",

  "Form.Custom.name": "Ünvan",
  "Form.Custom.vatNumber": "Vergi Numarası",
  "Form.Custom.gateNumber": "Kapı Kodu",
  "Form.Custom.parentId": "Ana Nokta",

  "Form.Custom.typeCode": "Tip",
  "Form.Custom.typeCode.ui:placeholder": "Tip seçin",
  "Form.Custom.typeCode.HEADQUARTER": "Genel Merkez",
  "Form.Custom.typeCode.CUSTOM": "Gümrük",

  "Form.Custom.Create": "Gümrük Oluştur",
  "Form.Custom.Update": "Gümrük Güncelle",

  "Form.TaxOffice.name": "Ünvan",
  "Form.TaxOffice.vatNumber": "Vergi Numarası",
  "Form.TaxOffice.taxOfficeId": "Vergi Dairesi",
  "Form.TaxOffice.externalStoreIdentifier": "Vergi Dairesi Kodu",
  "Form.TaxOffice.parentId": "Ana Nokta",
  "Form.TaxOffice.typeCode": "Tip",
  "Form.TaxOffice.typeCode.ui:placeholder": "Tip seçin",
  "Form.TaxOffice.typeCode.HEADQUARTER": "Genel Merkez",
  "Form.TaxOffice.typeCode.TAXOFFICE": "Vergi Dairesi",

  "Form.TaxOffice.Create": "Vergi Dairesi Oluştur",
  "Form.TaxOffice.Update": "Vergi Dairesi Güncelle",

  "Form.Individual": "Kişi",
  "Form.Individuals": "Kişiler",
  "Form.Individual.update": "Kişiyi güncelle",
  "Form.Individual.create": "Kişi oluştur",
  "Form.Individual.delete": "Kişiyi sil",
  "Form.Individual.delete.confirm": "Bu kişiyi silmek istediğinize emin misiniz?",
  "Form.Individual.firstname": "Ad",
  "Form.Individual.lastname": "Soyad",
  "Form.Individual.gender": "Cinsiyet",
  "Form.Individual.gender.ui:placeholder": "Cinsiyet seçin",
  "Form.Individual.gender.UNKNOWN": "Belirtmek istemiyorum",
  "Form.Individual.gender.MALE": "Erkek",
  "Form.Individual.gender.FEMALE": "Kadın",
  "Form.Individual.gender.OTHER": "Diğer",
  "Form.Individual.identificationNumber": "Kimlik Numarası",
  "Form.Individual.birthDate": "Doğum Tarihi",
  "Form.Individual.notes": "Notlar",
  "Form.Individual.createAccount": "Hesap Oluştur",
  "Form.Individual.newUser.username": "Kullanıcı Adı",
  "Form.Individual.newUser.password": "Şifre",

  "Form.Individual.Create": "Kişi Oluştur",
  "Form.Individual.Update": "Kişiyi Güncelle",

  "CRM.PartyStatus.DRAFT": "Taslak",
  "CRM.PartyStatus.WAITINGAPPROVAL": "Onay Bekliyor",
  "CRM.PartyStatus.APPROVED": "Onaylandı",
  "CRM.PartyStatus.REJECTED": "Reddedildi",
  "CRM.PartyStatus.ACTIVE": "Aktif",
  "CRM.PartyStatus.INACTIVE": "Pasif",
  "CRM.PartyStatus.SUSPENDED": "Askıya Alındı",

  "CRM.Affiliations.Drawer.cancel": "İptal",
  "CRM.Affiliations.Drawer.next": "Sonraki adım",
  "CRM.Affiliations.Drawer.previous": "Önceki adım",
  "CRM.Affiliations.createOrSelect": "Kişi Oluştur veya Seç",
  "CRM.Affiliations.selectUserAndRole": "Kullanıcı ve Rol Seç",
  "CRM.Affiliations.fillDetails": "Ayrıntıları Doldur",
  "CRM.Affiliations.selectRole": "Rol Seç",
  "CRM.Affiliation": "Bağlılık",
  "CRM.Affiliation.update": "Bağlılığı güncelle",
  "CRM.Affiliation.create": "Bağlılık ekle",
  "CRM.Affiliation.delete": "Bağlılığı sil",
  "CRM.Affiliation.delete.confirm": "Bu bağlılığı silmek istediğinize emin misiniz?",
  "CRM.Affiliation.abpRoleId": "Rol",
  "CRM.Affiliation.isPrimary": "Varsayılan",
  "CRM.Affiliation.startDate": "Başlangıç Tarihi",
  "CRM.Affiliation.endDate": "Bitiş Tarihi",
  "CRM.Affiliation.individuals": "Kişiler",
  "CRM.Affiliation.or": "veya",

  "CRM.Affiliations.search": "Bağlılık ara",
  "CRM.Affiliations.notFound": "Bağlılık bulunamadı.",
  "CRM.Affiliations.switchTo.{0}": "{0} ile işlem yap.",

  "CRM.Messages.email.isPrimary.atLeastOnePrimaryRequired": "Bu alan değiştirilemez çünkü en az bir varsayılan e-posta olmalıdır.",
  "CRM.Messages.address.isPrimary.atLeastOnePrimaryRequired": "Bu alan değiştirilemez çünkü en az bir varsayılan adres olmalıdır.",
  "CRM.Messages.telephone.isPrimary.atLeastOnePrimaryRequired": "Bu alan değiştirilemez çünkü en az bir varsayılan telefon olmalıdır.",
  "CRM.Messages.PhonesError.Title": "Telefonlar alınırken hata oluştu.",
  "CRM.Messages.PhonesError.Message": "Telefonlar alınırken bir hata oluştu. Lütfen daha sonra tekrar deneyin.",
  "CRM.Messages.EmailsError.Title": "E-postalar alınırken hata oluştu.",
  "CRM.Messages.EmailsError.Message": "E-postalar alınırken bir hata oluştu. Lütfen daha sonra tekrar deneyin.",
  "CRM.Messages.AddressesError.Title": "Adresler alınırken hata oluştu.",
  "CRM.Messages.AddressesError.Message": "Adresler alınırken bir hata oluştu. Lütfen daha sonra tekrar deneyin.",

  "CRM.Messages.MissingTaxOffice.Title": "Vergi Dairesi Yok",
  "CRM.Messages.MissingTaxOffice.Message": "Lütfen bir vergi dairesi oluşturun veya yöneticinizle iletişime geçin."
}
